chain.py
function_chain-0.1.0.dist-info/LICENSE.txt
function_chain-0.1.0.dist-info/METADATA
function_chain-0.1.0.dist-info/WHEEL
function_chain-0.1.0.dist-info/top_level.txt
function_chain-0.1.0.dist-info/RECORD
